LICENSE
MANIFEST.in
README.md
pyproject.toml
setup.py
pcdiff/__init__.py
pcdiff/grad_div_mls.py
pcdiff/operators.py
pcdiff/utils.py
pcdiff.egg-info/PKG-INFO
pcdiff.egg-info/SOURCES.txt
pcdiff.egg-info/dependency_links.txt
pcdiff.egg-info/not-zip-safe
pcdiff.egg-info/requires.txt
pcdiff.egg-info/top_level.txt
test/test_grad_div_mls.py
test/test_operators.py
test/test_utils.py