Metadata-Version: 2.1
Name: pcdiff
Version: 1.0.1
Summary: Simple and small library to compute differential operators (gradient, divergence, Laplacian) on point clouds.
Home-page: https://github.com/rubenwiersma/pcdiff
Author: Ruben Wiersma
Author-email: rubenwiersma@gmail.com
License: MIT
Project-URL: Bug Tracker, https://github.com/rubenwiersma/pcdiff
Platform: UNKNOWN
Classifier: Programming Language :: Python :: 3
Classifier: License :: OSI Approved :: Apache Software License
Classifier: Operating System :: OS Independent
Requires-Python: >=3.6
